<?xml version='1.0' encoding='UTF-8'?>
<image h="2090" w="1260"><stack><stack composite-op="svg:src-over" name="logo" opacity="1.0" visibility="visible"><layer composite-op="svg:src-over" name="twobytes" opacity="1.0" src="data/001-000.png" visibility="visible" x="168" y="88" /><layer composite-op="svg:src-over" name="consulting" opacity="1.0" src="data/001-001.png" visibility="visible" x="170" y="121" /></stack><stack composite-op="svg:src-over" name="search" opacity="1.0" visibility="visible"><stack composite-op="svg:src-over" name="location" opacity="1.0" visibility="visible"><layer composite-op="svg:src-over" name="line" opacity="1.0" src="data/002-001-000.png" visibility="visible" x="852" y="548" /><layer composite-op="svg:src-over" name="" opacity="1.0" src="data/002-001-001.png" visibility="visible" x="864" y="553" /><layer composite-op="svg:src-over" name="Select your Location" opacity="1.0" src="data/002-001-002.png" visibility="visible" x="657" y="549" /><layer composite-op="svg:src-over" name="Shape 4 #1" opacity="1.0" src="data/002-001-003.png" visibility="visible" x="639" y="535" /><layer composite-op="svg:src-over" name="Shape 4" opacity="1.0" src="data/002-001-004.png" visibility="visible" x="639" y="543" /></stack><stack composite-op="svg:src-over" name="option 2" opacity="1.0" visibility="visible"><layer composite-op="svg:src-over" name="check box #1" opacity="1.0" src="data/002-002-000.png" visibility="visible" x="269" y="545" /><layer composite-op="svg:src-over" name="check box shadow #1" opacity="1.0" src="data/002-002-001.png" visibility="visible" x="269" y="547" /><layer composite-op="svg:src-over" name="Part Time / Casual / Freelance" opacity="1.0" src="data/002-002-002.png" visibility="visible" x="299" y="549" /></stack><stack composite-op="svg:src-over" name="option 1" opacity="1.0" visibility="visible"><layer composite-op="svg:src-over" name="check box" opacity="1.0" src="data/002-003-000.png" visibility="visible" x="150" y="545" /><layer composite-op="svg:src-over" name="check box shadow" opacity="1.0" src="data/002-003-001.png" visibility="visible" x="150" y="547" /><layer composite-op="svg:src-over" name="Full Time" opacity="1.0" src="data/002-003-002.png" visibility="visible" x="180" y="550" /></stack><layer composite-op="svg:src-over" name="Enter a Job Description" opacity="1.0" src="data/002-003.png" visibility="visible" x="170" y="475" /><layer composite-op="svg:src-over" name="I’m looking for.." opacity="1.0" src="data/002-004.png" visibility="visible" x="152" y="362" /><layer composite-op="svg:src-over" name="icon" opacity="1.0" src="data/002-005.png" visibility="visible" x="997" y="476" /><stack composite-op="svg:src-over" name="search btn" opacity="1.0" visibility="visible"><layer composite-op="svg:src-over" name="Search" opacity="1.0" src="data/002-007-000.png" visibility="visible" x="1020" y="475" /><layer composite-op="svg:src-over" name="btn bg" opacity="1.0" src="data/002-007-001.png" visibility="visible" x="969" y="456" /><layer composite-op="svg:src-over" name="btn shadow" opacity="1.0" src="data/002-007-002.png" visibility="visible" x="969" y="460" /></stack><stack composite-op="svg:src-over" name="input btn" opacity="1.0" visibility="visible"><layer composite-op="svg:src-over" name="input bg #1" opacity="1.0" src="data/002-008-000.png" visibility="visible" x="149" y="456" /><layer composite-op="svg:src-over" name="input shadow" opacity="1.0" src="data/002-008-001.png" visibility="visible" x="149" y="460" /></stack></stack><stack composite-op="svg:src-over" name="nav" opacity="1.0" visibility="visible"><layer composite-op="svg:src-over" name="hover" opacity="1.0" src="data/003-000.png" visibility="visible" x="583" y="83" /><layer composite-op="svg:src-over" name="HOME      ABOUT US      JOBS      CLIENTS      EMPLOYERS      C" opacity="1.0" src="data/003-001.png" visibility="visible" x="585" y="100" /></stack><stack composite-op="svg:src-over" name="hero" opacity="1.0" visibility="visible"><layer composite-op="svg:src-over" name="header img bg" opacity="1.0" src="data/004-000.png" visibility="visible" x="0" y="0" /></stack><stack composite-op="svg:src-over" name="intro" opacity="1.0" visibility="visible"><layer composite-op="svg:src-over" name="separator one" opacity="1.0" src="data/005-000.png" visibility="visible" x="-19" y="853" /><layer composite-op="svg:src-over" name="We’re leaders in" opacity="1.0" src="data/005-001.png" visibility="visible" x="514" y="967" /><layer composite-op="svg:src-over" name="Creative Digital Recruitment" opacity="1.0" src="data/005-002.png" visibility="visible" x="314" y="1020" /><layer composite-op="svg:src-over" name="Shape 6" opacity="1.0" src="data/005-003.png" visibility="visible" x="560" y="1108" /><layer composite-op="svg:src-over" name="Based in Surry Hills, the creative hub of Sydney we are surroun" opacity="1.0" src="data/005-004.png" visibility="visible" x="283" y="1169" /><stack composite-op="svg:src-over" name="find out more btn" opacity="1.0" visibility="visible"><layer composite-op="svg:src-over" name="FIND OUT MORE ABOUT US!" opacity="1.0" src="data/005-006-000.png" visibility="visible" x="522" y="1312" /><layer composite-op="svg:src-over" name="btn" opacity="1.0" src="data/005-006-001.png" visibility="visible" x="489" y="1286" /></stack><layer composite-op="svg:src-over" name="separator two" opacity="1.0" src="data/005-006.png" visibility="visible" x="-19" y="1447" /><layer composite-op="svg:src-over" name="BG" opacity="1.0" src="data/005-007.png" visibility="visible" x="-3" y="851" /></stack><stack composite-op="svg:src-over" name="subscribe" opacity="1.0" visibility="visible"><layer composite-op="svg:src-over" name="Subscribe to our Job Seeker Mailing List" opacity="1.0" src="data/006-000.png" visibility="visible" x="452" y="1616" /><stack composite-op="svg:src-over" name="input" opacity="1.0" visibility="visible"><layer composite-op="svg:src-over" name="mail icon #1" opacity="1.0" src="data/006-002-000.png" visibility="visible" x="772" y="1689" /><layer composite-op="svg:src-over" name="Enter Your Email Address" opacity="1.0" src="data/006-002-001.png" visibility="visible" x="471" y="1689" /><layer composite-op="svg:src-over" name="input bg" opacity="1.0" src="data/006-002-002.png" visibility="visible" x="449" y="1668" /></stack><layer composite-op="svg:src-over" name="separator three" opacity="1.0" src="data/006-002.png" visibility="visible" x="-22" y="1897" /><layer composite-op="svg:src-over" name="bg #1" opacity="1.0" src="data/006-003.png" visibility="visible" x="-1" y="1453" /></stack><stack composite-op="svg:src-over" name="footer" opacity="1.0" visibility="visible"><stack composite-op="svg:src-over" name="Like #1" opacity="1.0" visibility="visible"><stack composite-op="svg:src-over" name="Button #1" opacity="1.0" visibility="visible"><layer composite-op="svg:src-over" name="Facebook" opacity="1.0" src="data/007-001-001-000.png" visibility="visible" x="1034" y="2012" /><layer composite-op="svg:src-over" name="Like" opacity="1.0" src="data/007-001-001-001.png" visibility="visible" x="1049" y="2014" /><layer composite-op="svg:src-over" name="Shape 2 #1" opacity="1.0" src="data/007-001-001-002.png" visibility="visible" x="1027" y="2008" /></stack><stack composite-op="svg:src-over" name="Counter #1" opacity="1.0" visibility="visible"><layer composite-op="svg:src-over" name="117" opacity="1.0" src="data/007-001-002-000.png" visibility="visible" x="1088" y="2013" /><layer composite-op="svg:src-over" name="Arrow #1" opacity="1.0" src="data/007-001-002-001.png" visibility="visible" x="1079" y="2014" /><layer composite-op="svg:src-over" name="Shape 3" opacity="1.0" src="data/007-001-002-002.png" visibility="visible" x="1083" y="2009" /></stack></stack><stack composite-op="svg:src-over" name="Tweet #1" opacity="1.0" visibility="visible"><stack composite-op="svg:src-over" name="Button" opacity="1.0" visibility="visible"><layer composite-op="svg:src-over" name="Twitterbird" opacity="1.0" src="data/007-002-001-000.png" visibility="visible" x="918" y="2013" /><layer composite-op="svg:src-over" name="Tweet" opacity="1.0" src="data/007-002-001-001.png" visibility="visible" x="933" y="2013" /><layer composite-op="svg:src-over" name="Shape 2" opacity="1.0" src="data/007-002-001-002.png" visibility="visible" x="914" y="2008" /></stack><stack composite-op="svg:src-over" name="Counter" opacity="1.0" visibility="visible"><layer composite-op="svg:src-over" name="692" opacity="1.0" src="data/007-002-002-000.png" visibility="visible" x="983" y="2013" /><layer composite-op="svg:src-over" name="Arrow" opacity="1.0" src="data/007-002-002-001.png" visibility="visible" x="972" y="2015" /><layer composite-op="svg:src-over" name="Shape 2 copy" opacity="1.0" src="data/007-002-002-002.png" visibility="visible" x="975" y="2008" /></stack></stack><layer composite-op="svg:src-over" name="Copyright © 2014 Two Bytes Consulting. Terms &amp; Policies." opacity="1.0" src="data/007-002.png" visibility="visible" x="151" y="2014" /><layer composite-op="svg:src-over" name="hello@twobytes.com.au" opacity="1.0" src="data/007-003.png" visibility="visible" x="185" y="1972" /><layer composite-op="svg:src-over" name="mail icon" opacity="1.0" src="data/007-004.png" visibility="visible" x="151" y="1969" /><layer composite-op="svg:src-over" name="bg" opacity="1.0" src="data/007-005.png" visibility="visible" x="-1" y="1903" /></stack></stack></image>